aws_cost_optimization_7/__init__.py
aws_cost_optimization_7/_ec2_costing.py
aws_cost_optimization_7/_kms_costing.py
aws_cost_optimization_7/_rds_costing.py
aws_cost_optimization_7/_ri_recommendations.py
aws_cost_optimization_7/_savings_plan.py
aws_cost_optimization_7/utils.py
aws_cost_optimization_7-0.2.1.dist-info/LICENCE
aws_cost_optimization_7-0.2.1.dist-info/METADATA
aws_cost_optimization_7-0.2.1.dist-info/WHEEL
aws_cost_optimization_7-0.2.1.dist-info/top_level.txt
aws_cost_optimization_7-0.2.1.dist-info/RECORD
